lightu2f.py
setup.py
lightu2f.egg-info/PKG-INFO
lightu2f.egg-info/SOURCES.txt
lightu2f.egg-info/dependency_links.txt
lightu2f.egg-info/top_level.txt