Metadata-Version: 1.1
Name: lightu2f
Version: 0.0.0
Summary: A lightweight FIDO U2F relying party library
Home-page: https://github.com/concise/lightu2f.py
Author: Jong-Shian Wu
Author-email: js@jong.sh
License: MIT
Platform: UNKNOWN
Classifier: Development Status :: 1 - Planning
Classifier: Intended Audience :: Developers
Classifier: Programming Language :: Python :: 3 :: Only
Classifier: Programming Language :: Python :: 3
Classifier: Programming Language :: Python :: 3.5
Classifier: Topic :: Internet
Classifier: Topic :: Security :: Cryptography
Classifier: Topic :: Security
Classifier: Topic :: System :: Systems Administration :: Authentication/Directory
